{"properties": [
  {
    "name": "slack.channel.monitor",
    "type": "java.lang.String",
    "description": "A description for 'slack.channel.monitor'"
  },
  {
    "name": "slack.token.location",
    "type": "java.lang.String",
    "description": "A description for 'slack.token.location'"
  },
  {
    "name": "image.user.originalFileName",
    "type": "java.lang.String",
    "description": "A description for 'image.user.originalFileName'"
  },
  {
    "name": "image.todo.path",
    "type": "java.lang.String",
    "description": "A description for 'image.todo.path'"
  },
  {
    "name": "image.user.path",
    "type": "java.lang.String",
    "description": "A description for 'image.user.path'"
  }
]}